easycluster/__init__.py
easycluster/__main__.py
easycluster/linux_service.py
easycluster/server.py
easycluster/solaris_service.py
easycluster/ssh.py
easycluster/windows_service.py
EasyCluster-0.22.3.dist-info/LICENSE
EasyCluster-0.22.3.dist-info/METADATA
EasyCluster-0.22.3.dist-info/WHEEL
EasyCluster-0.22.3.dist-info/entry_points.txt
EasyCluster-0.22.3.dist-info/top_level.txt
EasyCluster-0.22.3.dist-info/RECORD
